{
    "name": "Maria Kroczek",
    "title": "At vero eos et accusamus et",
    "text":"Lorem ipsum dolor sit amet, consectetur adipiscing elit, sed do eiusmod tempor incididunt ut labore et dolore magna aliqua. Ut enim ad minim veniam, quis nostrud exercitation ullamco laboris nisi ut aliquip ex ea commodo consequat. Duis aute irure dolor in reprehenderit in voluptate velit esse cillum dolore eu fugiat nulla pariatur. Excepteur sint occaecat cupidatat non proident, sunt in culpa qui officia deserunt mollit anim id est laborum.",
    "linked_in": "https://www.linkedin.com/in/maria-kroczek-405808208/",
    "github": "https://github.com/MarKr17",
    "contactEmail":"mariakroczek199@gmail.com",
    "programming_skills": [
        "Python",
        "JavaScript",
        "HTML",
        "CSS",
        "Java",
        "C++",
        "React",
        "Node.js",
        "SQL",
        "Git"
    ],
    "tools": [
        "Visual Studio Code",
        "PyCharm",
        "Eclipse",
        "Postman",
        "Figma",
        "Jupyter Notebook",
        "Docker",
        "GitHub",
        "Slack",
        "Trello"
    ],
    "languages": [
        {
            "name": "English",
            "level": "profesional"
        },
        {
            "name": "Polish",
            "level": "native"
        }
    ],
    "interests": [
        "Web Development",
        "Data Science",
        "Machine Learning",
        "Artificial Intelligence",
        "Cloud Computing",
        "Cybersecurity",
        "Blockchain",
        "Internet of Things (IoT)",
        "Augmented Reality (AR)",
        "Virtual Reality (VR)"
    ],
    "education": [
        {
            "name": "Master of Science in Computer Science",
            "institution": "University of XYZ",
            "year": 2022
        },
        {
            "name": "Bachelor of Science in Information Technology",
            "institution": "University of ABC",
            "year": 2020
        }
        
    ],
    "certifications":[
        {
            "name": "AWS Certified Solutions Architect",
            "institution": "Amazon Web Services",
            "year": 2023
        },
        {
            "name": "Certified Ethical Hacker (CEH)",
            "institution": "EC-Council",
            "year": 2023
        },
        {
            "name": "Google Data Analytics Professional Certificate",
            "institution": "Google",
            "year": 2023
        }
    ],
    "recent_activities":[
        {
            "name": "Completed a project on machine learning",
            "description": "Developed a machine learning model to predict housing prices using Python and scikit-learn.",
            "date": "2023-10-01",
            "link": ""
        },
        {
            "name": "Attended a conference on cloud computing",
            "description":"Developed a machine learning model to predict housing prices using Python and scikit-learn.",
            "date": "2023-09-15",
            "link": ""
        },
        {
            "name": "Published a research paper on AI ethics",
            "description":"Developed a machine learning model to predict housing prices using Python and scikit-learn.",
            "date": "2023-08-20",
            "link": ""
        },
        {
            "name": "Participated in a hackathon",
            "description":"Developed a machine learning model to predict housing prices using Python and scikit-learn.",
            "date": "2023-07-10",
            "link": ""
        }
    ]

}